LICENSE.txt
MANIFEST.in
README.txt
setup.py
tart_hardware_interface/__init__.py
tart_hardware_interface/highlevel_modes_api.py
tart_hardware_interface/permute.txt
tart_hardware_interface/stream_vis.py
tart_hardware_interface/tart_testbench.py
tart_hardware_interface/tartspi.py
tart_hardware_interface.egg-info/PKG-INFO
tart_hardware_interface.egg-info/SOURCES.txt
tart_hardware_interface.egg-info/dependency_links.txt
tart_hardware_interface.egg-info/requires.txt
tart_hardware_interface.egg-info/top_level.txt