Metadata-Version: 1.0
Name: tart-hardware-interface
Version: 0.1.8
Summary: Transient Array Radio Telescope Low-Level hardware interface
Home-page: http://github.com/tmolteno/TART
Author: Tim Molteno, Max Scheel, Pat Suggate
Author-email: tim@elec.ac.nz
License: GPLv3
Platform: UNKNOWN
